adapapi/__init__.py
adapapi/adapapi.py
adapapi-0.1.1.dist-info/METADATA
adapapi-0.1.1.dist-info/WHEEL
adapapi-0.1.1.dist-info/top_level.txt
adapapi-0.1.1.dist-info/RECORD
